stockgeist/__init__.py
stockgeist/analysis.py
stockgeist/client.py
stockgeist/responses.py
stockgeist_client_python-0.1.1.dist-info/LICENCE
stockgeist_client_python-0.1.1.dist-info/METADATA
stockgeist_client_python-0.1.1.dist-info/WHEEL
stockgeist_client_python-0.1.1.dist-info/top_level.txt
stockgeist_client_python-0.1.1.dist-info/RECORD
