Metadata-Version: 2.1
Name: stockgeist-client-python
Version: 0.1.1
Summary: StockGeist's REST API Python client.
Home-page: https://github.com/stockgeist/stockgeist-client-python
License: UNKNOWN
Project-URL: Bug Tracker, https://github.com/stockgeist/stockgeist-client-python/issues
Platform: UNKNOWN
Classifier: Programming Language :: Python :: 3
Classifier: License :: OSI Approved :: MIT License
Classifier: Operating System :: OS Independent
Requires-Python: >=3.6
Requires-Dist: requests (==2.25.1)
Requires-Dist: setuptools (~=52.0.0)
Requires-Dist: numpy (~=1.20.3)
Requires-Dist: pandas (~=1.2.4)
Requires-Dist: tqdm (~=4.61.1)
Requires-Dist: plotly (~=4.14.3)
Requires-Dist: cufflinks (~=0.17.3)
Requires-Dist: wordcloud (~=1.8.1)
Requires-Dist: termcolor (~=1.1.0)
Requires-Dist: python-dotenv (~=0.18.0)
